dakit/__init__.py
dakit/dataloader.py
dakit/dtyping.py
dakit/manipulation.py
dakit/vfuncs.py
dakit/utils/__init__.py
dakit/utils/dtutils.py
dakit/utils/funcutils.py
dakit/utils/xlsxutils.py
dakit-0.0.1.dist-info/LICENSE
dakit-0.0.1.dist-info/METADATA
dakit-0.0.1.dist-info/WHEEL
dakit-0.0.1.dist-info/top_level.txt
dakit-0.0.1.dist-info/RECORD
