Metadata-Version: 2.1
Name: dakit
Version: 0.0.1
Summary: A toolkit for data processing
Home-page: https://github.com/yourusername/dakit
Author: Hongda Zhang
Author-email: 1324904307@qq.com
Classifier: Programming Language :: Python :: 3
Classifier: License :: OSI Approved :: MIT License
Classifier: Operating System :: OS Independent
Requires-Python: >=3.8
License-File: LICENSE
Requires-Dist: numpy>=1.18.0
Requires-Dist: pandas>=1.0.0
Provides-Extra: dev
Requires-Dist: pytest; extra == "dev"
Requires-Dist: black; extra == "dev"
